{"metadata": {"page_hash": "001be94613c0016cdc1dadc399effb005c7c59ffefca45378bc7b2812c100754", "original_filename": "NYSE_AEG_2013.pdf", "page_no": 270, "num_pages": 358, "original_width": 609.44897, "original_height": 793.70099, "coco_width": 1025, "coco_height": 1025, "collection": "ann_reports_10_14_fancy", "doc_category": "financial_reports"}, "form": [{"id_box": 226874, "box": [71.51146715368145, 30.234517850355815, 529.4478978280987, 14.631782492799971], "id_box_line": 0, "box_line": [119.1859400467934, 30.880227010930298, 422.639730361674, 13.986073332225487], "text": "Notes to the consolidated financial statements of Aegon N.V. ", "category": "Page-header", "words": [], "linking": [], "font": {"color": [161, 165, 167, 255], "name": "/JJSLPI+SenticoSansDT-Light", "size": 1}}, {"id_box": 226874, "box": [71.51146715368145, 30.234517850355815, 529.4478978280987, 14.631782492799971], "id_box_line": 1, "box_line": [541.8256704084674, 30.234517850355815, 59.13369457331271, 14.618855395405376], "text": "Note 50", "category": "Page-header", "words": [], "linking": [], "font": {"color": [0, 112, 186, 255], "name": "/JJSLPI+SenticoSansDT-Bold", "size": 1}}, {"id_box": 226874, "box": [71.51146715368145, 30.234517850355815, 529.4478978280987, 14.631782492799971], "id_box_line": 82, "box_line": [71.51146715368145, 31.405408099592023, 25.883625621682484, 13.157034426780683], "text": "270", "category": "Page-header", "words": [], "linking": [], "font": {"color": [135, 135, 135, 255], "name": "/JJSLPI+SenticoSansDT-Bold", "size": 1}}, {"id_box": 226875, "box": [119.1859400467934, 98.79476715784381, 694.04606155951, 14.618868309588493], "id_box_line": 2, "box_line": [119.1859400467934, 98.79476715784381, 19.854886496895716, 14.618868309588493], "text": "50", "category": "Section-header", "words": [], "linking": [], "font": {"color": [0, 112, 186, 255], "name": "/JJSLPI+SenticoSansDT-Bold", "size": 1}}, {"id_box": 226875, "box": [119.1859400467934, 98.79476715784381, 694.04606155951, 14.618868309588493], "id_box_line": 3, "box_line": [143.07909791036317, 98.79476715784381, 670.1529036959403, 14.618868309588493], "text": "Summary of total financial assets and financial liabilities at fair value through profit or loss", "category": "Section-header", "words": [], "linking": [], "font": {"color": [0, 112, 186, 255], "name": "/JJSLPI+SenticoSansDT-Bold", "size": 1}}, {"id_box": 226876, "box": [119.18612000443613, 363.4321836993048, 212.47278820571307, 13.156995684231106], "id_box_line": 53, "box_line": [119.18612000443613, 363.4321836993048, 212.47278820571307, 13.156995684231106], "text": "Investments for general account", "category": "Section-header", "words": [], "linking": [], "font": {"color": [0, 112, 186, 255], "name": "/JJSLPI+SenticoSansDT-Bold", "size": 1}}, {"id_box": 226877, "box": [119.18612000443613, 564.8934805410789, 268.94300875592586, 13.156956941681472], "id_box_line": 64, "box_line": [119.18612000443613, 564.8934805410789, 268.94300875592586, 13.156956941681472], "text": "Investments for account of policyholders", "category": "Section-header", "words": [], "linking": [], "font": {"color": [0, 112, 186, 255], "name": "/JJSLPI+SenticoSansDT-Bold", "size": 1}}, {"id_box": 226878, "box": [119.18612000443613, 719.8636790789438, 326.65744299313525, 13.156969855864759], "id_box_line": 72, "box_line": [119.18612000443613, 719.8636790789438, 326.65744299313525, 13.156969855864759], "text": "Investment contracts for account of policyholders", "category": "Section-header", "words": [], "linking": [], "font": {"color": [0, 112, 186, 255], "name": "/JJSLPI+SenticoSansDT-Bold", "size": 1}}, {"id_box": 226879, "box": [119.18612000443613, 797.3487783478763, 74.60841541007116, 13.156969855864702], "id_box_line": 76, "box_line": [119.18612000443613, 797.3487783478763, 74.60841541007116, 13.156969855864702], "text": "Derivatives", "category": "Section-header", "words": [], "linking": [], "font": {"color": [0, 112, 186, 255], "name": "/JJSLPI+SenticoSansDT-Bold", "size": 1}}, {"id_box": 226880, "box": [119.18612000443613, 859.3368577630224, 78.01415584474611, 13.15696985586473], "id_box_line": 79, "box_line": [119.18612000443613, 859.3368577630224, 78.01415584474611, 13.15696985586473], "text": "Borrowings ", "category": "Section-header", "words": [], "linking": [], "font": {"color": [0, 112, 186, 255], "name": "/JJSLPI+SenticoSansDT-Bold", "size": 1}}, {"id_box": 226881, "box": [119.1859400467934, 116.6227841671207, 770.080772472222, 42.88220397709222], "id_box_line": 4, "box_line": [119.1859400467934, 116.6227841671207, 770.080772472222, 11.88816426951928], "text": "The table that follows summarizes the carrying amounts of financial assets and financial liabilities that are classified as at fair value ", "category": "Text", "words": [], "linking": [], "font": {"color": [0, 0, 0, 255], "name": "/JJSLPI+SenticoSansDT-Light", "size": 1}}, {"id_box": 226881, "box": [119.1859400467934, 116.6227841671207, 770.080772472222, 42.88220397709222], "id_box_line": 5, "box_line": [119.1859400467934, 132.11980402090728, 764.0765614059533, 11.888164269519166], "text": "through profit or loss, with appropriate distinction between those financial assets and financial liabilities held for trading and those ", "category": "Text", "words": [], "linking": [], "font": {"color": [0, 0, 0, 255], "name": "/JJSLPI+SenticoSansDT-Light", "size": 1}}, {"id_box": 226881, "box": [119.1859400467934, 116.6227841671207, 770.080772472222, 42.88220397709222], "id_box_line": 6, "box_line": [119.1859400467934, 147.61682387469375, 485.4105370790929, 11.888164269519166], "text": "that, upon initial recognition, were designated as at fair value through profit or loss.", "category": "Text", "words": [], "linking": [], "font": {"color": [0, 0, 0, 255], "name": "/JJSLPI+SenticoSansDT-Light", "size": 1}}, {"id_box": 226882, "box": [119.18612000443613, 380.07216042404093, 768.1352335782929, 73.87620494211546], "id_box_line": 54, "box_line": [119.18612000443613, 380.07216042404093, 724.1029452802259, 11.888125526969475], "text": "The Group manages certain portfolios on a total return basis which have been designated at fair value through profit or loss. ", "category": "Text", "words": [], "linking": [], "font": {"color": [0, 0, 0, 255], "name": "/JJSLPI+SenticoSansDT-Light", "size": 1}}, {"id_box": 226882, "box": [119.18612000443613, 380.07216042404093, 768.1352335782929, 73.87620494211546], "id_box_line": 55, "box_line": [119.18612000443613, 395.5691802778274, 736.5002104688108, 11.888125526969588], "text": "This includes portfolios of investments in limited partnerships and limited liability companies (primarily hedge funds) for which ", "category": "Text", "words": [], "linking": [], "font": {"color": [0, 0, 0, 255], "name": "/JJSLPI+SenticoSansDT-Light", "size": 1}}, {"id_box": 226882, "box": [119.18612000443613, 380.07216042404093, 768.1352335782929, 73.87620494211546], "id_box_line": 56, "box_line": [119.18612000443613, 411.06620013161387, 751.5678452537214, 11.888125526969588], "text": "the performance is assessed internally on a total return basis. In addition, some investments that include an embedded derivative ", "category": "Text", "words": [], "linking": [], "font": {"color": [0, 0, 0, 255], "name": "/JJSLPI+SenticoSansDT-Light", "size": 1}}, {"id_box": 226882, "box": [119.18612000443613, 380.07216042404093, 768.1352335782929, 73.87620494211546], "id_box_line": 57, "box_line": [119.18612000443613, 426.56321998540034, 768.1352335782929, 11.888125526969588], "text": "that would otherwise have required bifurcation, such as convertible instruments, preferred shares and credit linked notes, have been ", "category": "Text", "words": [], "linking": [], "font": {"color": [0, 0, 0, 255], "name": "/JJSLPI+SenticoSansDT-Light", "size": 1}}, {"id_box": 226882, "box": [119.18612000443613, 380.07216042404093, 768.1352335782929, 73.87620494211546], "id_box_line": 58, "box_line": [119.18612000443613, 442.0602398391869, 270.2888228279391, 11.888125526969475], "text": "designated at fair value through profit or loss. ", "category": "Text", "words": [], "linking": [], "font": {"color": [0, 0, 0, 255], "name": "/JJSLPI+SenticoSansDT-Light", "size": 1}}, {"id_box": 226883, "box": [119.18612000443613, 473.05427954675986, 784.7767409058054, 73.87620494211558], "id_box_line": 59, "box_line": [119.18612000443613, 473.05427954675986, 753.0117446502534, 11.888125526969588], "text": "Investments for general account backing insurance and investment liabilities, that are carried at fair value with changes in the fair ", "category": "Text", "words": [], "linking": [], "font": {"color": [0, 0, 0, 255], "name": "/JJSLPI+SenticoSansDT-Light", "size": 1}}, {"id_box": 226883, "box": [119.18612000443613, 473.05427954675986, 784.7767409058054, 73.87620494211558], "id_box_line": 60, "box_line": [119.18612000443613, 488.5512994005463, 761.8035668761569, 11.888125526969588], "text": "value recognized in the income statement, are designated at fair value through profit or loss. The Group elected to designate these ", "category": "Text", "words": [], "linking": [], "font": {"color": [0, 0, 0, 255], "name": "/JJSLPI+SenticoSansDT-Light", "size": 1}}, {"id_box": 226883, "box": [119.18612000443613, 473.05427954675986, 784.7767409058054, 73.87620494211558], "id_box_line": 61, "box_line": [119.18612000443613, 504.0483192543329, 784.7767409058054, 11.888125526969532], "text": "investments at fair value through profit or loss, as a classification of financial assets as available-for-sale would result in accumulation ", "category": "Text", "words": [], "linking": [], "font": {"color": [0, 0, 0, 255], "name": "/JJSLPI+SenticoSansDT-Light", "size": 1}}, {"id_box": 226883, "box": [119.18612000443613, 473.05427954675986, 784.7767409058054, 73.87620494211558], "id_box_line": 62, "box_line": [119.18612000443613, 519.5453391081194, 761.4175997786984, 11.888125526969532], "text": "of unrealized gains and losses in a revaluation reserve within equity whilst changes to the liability would be reflected in net income ", "category": "Text", "words": [], "linking": [], "font": {"color": [0, 0, 0, 255], "name": "/JJSLPI+SenticoSansDT-Light", "size": 1}}, {"id_box": 226883, "box": [119.18612000443613, 473.05427954675986, 784.7767409058054, 73.87620494211558], "id_box_line": 63, "box_line": [119.18612000443613, 535.0423589619058, 134.65119881160842, 11.888125526969588], "text": "(accounting mismatch).", "category": "Text", "words": [], "linking": [], "font": {"color": [0, 0, 0, 255], "name": "/JJSLPI+SenticoSansDT-Light", "size": 1}}, {"id_box": 226884, "box": [119.18612000443613, 581.5334185232654, 764.9343421238369, 58.37918508832905], "id_box_line": 65, "box_line": [119.18612000443613, 581.5334185232654, 743.4907912388464, 11.888125526969532], "text": "Investments held for account of policyholders comprise assets that are linked to various insurance and investment contracts for ", "category": "Text", "words": [], "linking": [], "font": {"color": [0, 0, 0, 255], "name": "/JJSLPI+SenticoSansDT-Light", "size": 1}}, {"id_box": 226884, "box": [119.18612000443613, 581.5334185232654, 764.9343421238369, 58.37918508832905], "id_box_line": 66, "box_line": [119.18612000443613, 597.0304383770518, 764.9343421238369, 11.888125526969588], "text": "which the financial risks are borne by the customer. Under the Group\u2019s accounting policies these insurance and investment liabilities ", "category": "Text", "words": [], "linking": [], "font": {"color": [0, 0, 0, 255], "name": "/JJSLPI+SenticoSansDT-Light", "size": 1}}, {"id_box": 226884, "box": [119.18612000443613, 581.5334185232654, 764.9343421238369, 58.37918508832905], "id_box_line": 67, "box_line": [119.18612000443613, 612.5274582308384, 751.3820516014654, 11.888125526969532], "text": "are measured at the fair value of the linked assets with changes in the fair value recognized in the income statement. To avoid an ", "category": "Text", "words": [], "linking": [], "font": {"color": [0, 0, 0, 255], "name": "/JJSLPI+SenticoSansDT-Light", "size": 1}}, {"id_box": 226884, "box": [119.18612000443613, 581.5334185232654, 764.9343421238369, 58.37918508832905], "id_box_line": 68, "box_line": [119.18612000443613, 628.0244780846249, 577.1316898361482, 11.888125526969588], "text": "accounting mismatch the linked assets have been designated as at fair value through profit or loss. ", "category": "Text", "words": [], "linking": [], "font": {"color": [0, 0, 0, 255], "name": "/JJSLPI+SenticoSansDT-Light", "size": 1}}, {"id_box": 226885, "box": [119.18612000443613, 659.0185177921978, 767.4632851951492, 42.88217814872576], "id_box_line": 69, "box_line": [119.18612000443613, 659.0185177921978, 762.8600696051714, 11.888125526969588], "text": "In addition, the investment for account of policyholders include with profit assets, where an insurer manages these assets together ", "category": "Text", "words": [], "linking": [], "font": {"color": [0, 0, 0, 255], "name": "/JJSLPI+SenticoSansDT-Light", "size": 1}}, {"id_box": 226885, "box": [119.18612000443613, 659.0185177921978, 767.4632851951492, 42.88217814872576], "id_box_line": 70, "box_line": [119.18612000443613, 674.5155376459843, 767.4632851951492, 11.888125526969532], "text": "with related liabilities on a fair value basis in accordance with a documented policy of asset and liability management. In accordance ", "category": "Text", "words": [], "linking": [], "font": {"color": [0, 0, 0, 255], "name": "/JJSLPI+SenticoSansDT-Light", "size": 1}}, {"id_box": 226885, "box": [119.18612000443613, 659.0185177921978, 767.4632851951492, 42.88217814872576], "id_box_line": 71, "box_line": [119.18612000443613, 690.0125574997708, 614.5436055540466, 11.888138441152762], "text": "with Group\u2019s accounting policies, these assets have been designated as at fair value through profit or loss.", "category": "Text", "words": [], "linking": [], "font": {"color": [0, 0, 0, 255], "name": "/JJSLPI+SenticoSansDT-Light", "size": 1}}, {"id_box": 226886, "box": [119.18612000443613, 736.503604146947, 787.2356518626981, 42.88219106290896], "id_box_line": 73, "box_line": [119.18612000443613, 736.503604146947, 755.4420305690236, 11.888151355335935], "text": "With the exception of the financial liabilities with discretionary participating features that are not subject to the classification and ", "category": "Text", "words": [], "linking": [], "font": {"color": [0, 0, 0, 255], "name": "/JJSLPI+SenticoSansDT-Light", "size": 1}}, {"id_box": 226886, "box": [119.18612000443613, 736.503604146947, 787.2356518626981, 42.88219106290896], "id_box_line": 74, "box_line": [119.18612000443613, 752.0006240007335, 787.2356518626981, 11.888151355335992], "text": "measurement requirements for financial instruments, all investment contracts for account of policyholders that are carried at fair value ", "category": "Text", "words": [], "linking": [], "font": {"color": [0, 0, 0, 255], "name": "/JJSLPI+SenticoSansDT-Light", "size": 1}}, {"id_box": 226886, "box": [119.18612000443613, 736.503604146947, 787.2356518626981, 42.88219106290896], "id_box_line": 75, "box_line": [119.18612000443613, 767.4976438545201, 408.656892020016, 11.888151355335964], "text": "or at the fair value of the linked assets are included in the table above.", "category": "Text", "words": [], "linking": [], "font": {"color": [0, 0, 0, 255], "name": "/JJSLPI+SenticoSansDT-Light", "size": 1}}, {"id_box": 226887, "box": [119.18612000443613, 813.9887034158796, 775.3987781372409, 27.38517120912246], "id_box_line": 77, "box_line": [119.18612000443613, 813.9887034158796, 775.3987781372409, 11.888151355335964], "text": "With the exception of derivatives designated as a hedging instrument, all derivatives held for general account and held for account of ", "category": "Text", "words": [], "linking": [], "font": {"color": [0, 0, 0, 255], "name": "/JJSLPI+SenticoSansDT-Light", "size": 1}}, {"id_box": 226887, "box": [119.18612000443613, 813.9887034158796, 775.3987781372409, 27.38517120912246], "id_box_line": 78, "box_line": [119.18612000443613, 829.4857232696661, 261.3682888413118, 11.888151355335964], "text": "policyholders are included in the table above.", "category": "Text", "words": [], "linking": [], "font": {"color": [0, 0, 0, 255], "name": "/JJSLPI+SenticoSansDT-Light", "size": 1}}, {"id_box": 226888, "box": [119.18612000443613, 875.9767828310256, 753.940965188603, 27.38517250054079], "id_box_line": 80, "box_line": [119.18612000443613, 875.9767828310256, 753.940965188603, 11.888151355335992], "text": "Borrowings designated as at fair value through profit or loss includes financial instruments that are managed on a fair value basis ", "category": "Text", "words": [], "linking": [], "font": {"color": [0, 0, 0, 255], "name": "/JJSLPI+SenticoSansDT-Light", "size": 1}}, {"id_box": 226888, "box": [119.18612000443613, 875.9767828310256, 753.940965188603, 27.38517250054079], "id_box_line": 81, "box_line": [119.18612000443613, 891.4738026848121, 470.50582787103565, 11.888152646754293], "text": "together with related financial assets and financial derivatives (Refer to note 41).", "category": "Text", "words": [], "linking": [], "font": {"color": [0, 0, 0, 255], "name": "/JJSLPI+SenticoSansDT-Light", "size": 1}}, {"id_box": 226889, "box": [200.2324780366763, 991.0935549859904, 124.84539599763372, 12.587453084819767], "id_box_line": 83, "box_line": [200.2324780366763, 991.0935549859904, 124.84539599763372, 12.587453084819767], "text": "Annual Report 2013", "category": "Page-footer", "words": [], "linking": [], "font": {"color": [161, 165, 167, 255], "name": "/JJSLPI+SenticoSansDT-Light", "size": 1}}, {"id_box": 226892, "box": [116.93084957888988, 178.1004571977685, 787.8455602774384, 162.89078809137152], "id_box_line": 7, "box_line": [631.0463655390213, 179.76205970210526, 32.47984855893674, 12.052820105465798], "text": "2013", "category": "Table", "words": [], "linking": [], "font": {"color": [0, 112, 186, 255], "name": "/JJSLPI+SenticoSansDT-Regular", "size": 1}}, {"id_box": 226892, "box": [116.93084957888988, 178.1004571977685, 787.8455602774384, 162.89078809137152], "id_box_line": 8, "box_line": [803.5500449693105, 180.33414510419107, 30.569236584319697, 11.343818532971682], "text": "2012", "category": "Table", "words": [], "linking": [], "font": {"color": [0, 0, 0, 255], "name": "/JJSLPI+SenticoSansDT-Regular", "size": 1}}, {"id_box": 226892, "box": [116.93084957888988, 178.1004571977685, 787.8455602774384, 162.89078809137152], "id_box_line": 9, "box_line": [591.0621487308445, 194.88467155622436, 46.68974130844788, 12.42604000027768], "text": "Trading", "category": "Table", "words": [], "linking": [], "font": {"color": [0, 112, 186, 255], "name": "/JJSLPI+SenticoSansDT-Bold", "size": 1}}, {"id_box": 226892, "box": [116.93084957888988, 178.1004571977685, 787.8455602774384, 162.89078809137152], "id_box_line": 10, "box_line": [653.6921175697449, 194.88467155622436, 69.83448056364762, 12.42604000027768], "text": "Designated", "category": "Table", "words": [], "linking": [], "font": {"color": [0, 112, 186, 255], "name": "/JJSLPI+SenticoSansDT-Bold", "size": 1}}, {"id_box": 226892, "box": [116.93084957888988, 178.1004571977685, 787.8455602774384, 162.89078809137152], "id_box_line": 11, "box_line": [768.9896001465061, 195.9952009131299, 40.31052878799676, 11.188848334433828], "text": "Trading", "category": "Table", "words": [], "linking": [], "font": {"color": [0, 0, 0, 255], "name": "/JJSLPI+SenticoSansDT-Light", "size": 1}}, {"id_box": 226892, "box": [116.93084957888988, 178.1004571977685, 787.8455602774384, 162.89078809137152], "id_box_line": 12, "box_line": [833.6134155743999, 195.9952009131299, 61.461438272674286, 11.188848334433828], "text": "Designated", "category": "Table", "words": [], "linking": [], "font": {"color": [0, 0, 0, 255], "name": "/JJSLPI+SenticoSansDT-Light", "size": 1}}, {"id_box": 226892, "box": [116.93084957888988, 178.1004571977685, 787.8455602774384, 162.89078809137152], "id_box_line": 13, "box_line": [119.1859400467934, 212.05279963176065, 165.67034127566086, 10.489545313531721], "text": "Investments for general account", "category": "Table", "words": [], "linking": [], "font": {"color": [0, 0, 0, 255], "name": "/JJSLPI+SenticoSansDT-Light", "size": 1}}, {"id_box": 226892, "box": [116.93084957888988, 178.1004571977685, 787.8455602774384, 162.89078809137152], "id_box_line": 14, "box_line": [616.6356434239276, 212.05279963176065, 21.11557387651351, 10.489545313531721], "text": "121", "category": "Table", "words": [], "linking": [], "font": {"color": [0, 0, 0, 255], "name": "/JJSLPI+SenticoSansDT-Light", "size": 1}}, {"id_box": 226892, "box": [116.93084957888988, 178.1004571977685, 787.8455602774384, 162.89078809137152], "id_box_line": 15, "box_line": [692.6595064226624, 212.05279963176065, 30.86611623939575, 10.489545313531721], "text": "4,712", "category": "Table", "words": [], "linking": [], "font": {"color": [0, 0, 0, 255], "name": "/JJSLPI+SenticoSansDT-Light", "size": 1}}, {"id_box": 226892, "box": [116.93084957888988, 178.1004571977685, 787.8455602774384, 162.89078809137152], "id_box_line": 16, "box_line": [788.1840505038509, 212.05279963176065, 21.11557387651351, 10.489545313531721], "text": "754", "category": "Table", "words": [], "linking": [], "font": {"color": [0, 0, 0, 255], "name": "/JJSLPI+SenticoSansDT-Light", "size": 1}}, {"id_box": 226892, "box": [116.93084957888988, 178.1004571977685, 787.8455602774384, 162.89078809137152], "id_box_line": 17, "box_line": [864.2078630471718, 212.05279963176065, 30.866065783981867, 10.489545313531721], "text": "4,809", "category": "Table", "words": [], "linking": [], "font": {"color": [0, 0, 0, 255], "name": "/JJSLPI+SenticoSansDT-Light", "size": 1}}, {"id_box": 226892, "box": [116.93084957888988, 178.1004571977685, 787.8455602774384, 162.89078809137152], "id_box_line": 18, "box_line": [119.18612000443613, 227.54863138069163, 209.22473775778138, 10.489545313531835], "text": "Investments for account of policyholders", "category": "Table", "words": [], "linking": [], "font": {"color": [0, 0, 0, 255], "name": "/JJSLPI+SenticoSansDT-Light", "size": 1}}, {"id_box": 226892, "box": [116.93084957888988, 178.1004571977685, 787.8455602774384, 162.89078809137152], "id_box_line": 19, "box_line": [633.1850023472842, 227.54863138069163, 4.566214953156873, 10.489545313531835], "text": "-", "category": "Table", "words": [], "linking": [], "font": {"color": [0, 0, 0, 255], "name": "/JJSLPI+SenticoSansDT-Light", "size": 1}}, {"id_box": 226892, "box": [116.93084957888988, 178.1004571977685, 787.8455602774384, 162.89078809137152], "id_box_line": 20, "box_line": [678.5824123223967, 227.54863138069163, 44.94315988424751, 10.489545313531835], "text": "164,037", "category": "Table", "words": [], "linking": [], "font": {"color": [0, 0, 0, 255], "name": "/JJSLPI+SenticoSansDT-Light", "size": 1}}, {"id_box": 226892, "box": [116.93084957888988, 178.1004571977685, 787.8455602774384, 162.89078809137152], "id_box_line": 21, "box_line": [804.7334094272076, 227.54863138069163, 4.566214953156873, 10.489545313531835], "text": "-", "category": "Table", "words": [], "linking": [], "font": {"color": [0, 0, 0, 255], "name": "/JJSLPI+SenticoSansDT-Light", "size": 1}}, {"id_box": 226892, "box": [116.93084957888988, 178.1004571977685, 787.8455602774384, 162.89078809137152], "id_box_line": 22, "box_line": [850.1308194023201, 227.54863138069163, 44.94310942883362, 10.489545313531835], "text": "151,960", "category": "Table", "words": [], "linking": [], "font": {"color": [0, 0, 0, 255], "name": "/JJSLPI+SenticoSansDT-Light", "size": 1}}, {"id_box": 226892, "box": [116.93084957888988, 178.1004571977685, 787.8455602774384, 162.89078809137152], "id_box_line": 23, "box_line": [119.18612000443613, 243.0443985587067, 293.3856462584554, 10.48953239934849], "text": "Derivatives with positive values not designated as hedges", "category": "Table", "words": [], "linking": [], "font": {"color": [0, 0, 0, 255], "name": "/JJSLPI+SenticoSansDT-Light", "size": 1}}, {"id_box": 226892, "box": [116.93084957888988, 178.1004571977685, 787.8455602774384, 162.89078809137152], "id_box_line": 24, "box_line": [599.8467221956253, 243.0443985587067, 37.90464647105739, 10.48953239934849], "text": "12,651", "category": "Table", "words": [], "linking": [], "font": {"color": [0, 0, 0, 255], "name": "/JJSLPI+SenticoSansDT-Light", "size": 1}}, {"id_box": 226892, "box": [116.93084957888988, 178.1004571977685, 787.8455602774384, 162.89078809137152], "id_box_line": 25, "box_line": [718.959205887246, 243.0443985587067, 4.566214953156759, 10.48953239934849], "text": "-", "category": "Table", "words": [], "linking": [], "font": {"color": [0, 0, 0, 255], "name": "/JJSLPI+SenticoSansDT-Light", "size": 1}}, {"id_box": 226892, "box": [116.93084957888988, 178.1004571977685, 787.8455602774384, 162.89078809137152], "id_box_line": 26, "box_line": [771.3951292755486, 243.0443985587067, 37.90464647105739, 10.48953239934849], "text": "19,348", "category": "Table", "words": [], "linking": [], "font": {"color": [0, 0, 0, 255], "name": "/JJSLPI+SenticoSansDT-Light", "size": 1}}, {"id_box": 226892, "box": [116.93084957888988, 178.1004571977685, 787.8455602774384, 162.89078809137152], "id_box_line": 27, "box_line": [890.5075625117554, 243.0443985587067, 4.566265408570757, 10.48953239934849], "text": "-", "category": "Table", "words": [], "linking": [], "font": {"color": [0, 0, 0, 255], "name": "/JJSLPI+SenticoSansDT-Light", "size": 1}}, {"id_box": 226892, "box": [116.93084957888988, 178.1004571977685, 787.8455602774384, 162.89078809137152], "id_box_line": 28, "box_line": [119.1859400467934, 256.86786941011644, 346.5849550127224, 12.426040000277567], "text": "Total financial assets at fair value through profit or loss", "category": "Table", "words": [], "linking": [], "font": {"color": [0, 112, 186, 255], "name": "/JJSLPI+SenticoSansDT-Bold", "size": 1}}, {"id_box": 226892, "box": [116.93084957888988, 178.1004571977685, 787.8455602774384, 162.89078809137152], "id_box_line": 29, "box_line": [594.5348098627519, 257.46194766621136, 43.21671017017229, 11.695045573774564], "text": "12,771", "category": "Table", "words": [], "linking": [], "font": {"color": [0, 112, 186, 255], "name": "/JJSLPI+SenticoSansDT-Bold", "size": 1}}, {"id_box": 226892, "box": [116.93084957888988, 178.1004571977685, 787.8455602774384, 162.89078809137152], "id_box_line": 30, "box_line": [672.3706949574465, 257.46194766621136, 51.15502861543928, 11.695045573774564], "text": "168,749", "category": "Table", "words": [], "linking": [], "font": {"color": [0, 112, 186, 255], "name": "/JJSLPI+SenticoSansDT-Bold", "size": 1}}, {"id_box": 226892, "box": [116.93084957888988, 178.1004571977685, 787.8455602774384, 162.89078809137152], "id_box_line": 31, "box_line": [766.0832169426752, 257.46194766621136, 43.21671017017229, 11.695045573774564], "text": "20,102", "category": "Table", "words": [], "linking": [], "font": {"color": [0, 112, 186, 255], "name": "/JJSLPI+SenticoSansDT-Bold", "size": 1}}, {"id_box": 226892, "box": [116.93084957888988, 178.1004571977685, 787.8455602774384, 162.89078809137152], "id_box_line": 32, "box_line": [843.9191020373698, 257.46194766621136, 51.15502861543939, 11.695045573774564], "text": "156,769", "category": "Table", "words": [], "linking": [], "font": {"color": [0, 112, 186, 255], "name": "/JJSLPI+SenticoSansDT-Bold", "size": 1}}, {"id_box": 226892, "box": [116.93084957888988, 178.1004571977685, 787.8455602774384, 162.89078809137152], "id_box_line": 33, "box_line": [119.1859400467934, 281.7857600883174, 254.86289910375928, 10.489545313531835], "text": "Investment contracts for account of policyholders", "category": "Table", "words": [], "linking": [], "font": {"color": [0, 0, 0, 255], "name": "/JJSLPI+SenticoSansDT-Light", "size": 1}}, {"id_box": 226892, "box": [116.93084957888988, 178.1004571977685, 787.8455602774384, 162.89078809137152], "id_box_line": 34, "box_line": [633.1850023472842, 281.7857600883174, 4.566214953156873, 10.489545313531835], "text": "-", "category": "Table", "words": [], "linking": [], "font": {"color": [0, 0, 0, 255], "name": "/JJSLPI+SenticoSansDT-Light", "size": 1}}, {"id_box": 226892, "box": [116.93084957888988, 178.1004571977685, 787.8455602774384, 162.89078809137152], "id_box_line": 35, "box_line": [685.620925735587, 281.7857600883174, 37.904646471057276, 10.489545313531835], "text": "32,628", "category": "Table", "words": [], "linking": [], "font": {"color": [0, 0, 0, 255], "name": "/JJSLPI+SenticoSansDT-Light", "size": 1}}, {"id_box": 226892, "box": [116.93084957888988, 178.1004571977685, 787.8455602774384, 162.89078809137152], "id_box_line": 36, "box_line": [804.7334094272076, 281.7857600883174, 4.566214953156873, 10.489545313531835], "text": "-", "category": "Table", "words": [], "linking": [], "font": {"color": [0, 0, 0, 255], "name": "/JJSLPI+SenticoSansDT-Light", "size": 1}}, {"id_box": 226892, "box": [116.93084957888988, 178.1004571977685, 787.8455602774384, 162.89078809137152], "id_box_line": 37, "box_line": [857.1693328155103, 281.7857600883174, 37.90459601564339, 10.489545313531835], "text": "29,188", "category": "Table", "words": [], "linking": [], "font": {"color": [0, 0, 0, 255], "name": "/JJSLPI+SenticoSansDT-Light", "size": 1}}, {"id_box": 226892, "box": [116.93084957888988, 178.1004571977685, 787.8455602774384, 162.89078809137152], "id_box_line": 38, "box_line": [119.1859400467934, 297.2815143521493, 297.30849918410723, 10.489545313531607], "text": "Derivatives with negative values not designated as hedges", "category": "Table", "words": [], "linking": [], "font": {"color": [0, 0, 0, 255], "name": "/JJSLPI+SenticoSansDT-Light", "size": 1}}, {"id_box": 226892, "box": [116.93084957888988, 178.1004571977685, 787.8455602774384, 162.89078809137152], "id_box_line": 39, "box_line": [599.8467221956253, 297.2815143521493, 37.90464647105739, 10.489545313531607], "text": "11,248", "category": "Table", "words": [], "linking": [], "font": {"color": [0, 0, 0, 255], "name": "/JJSLPI+SenticoSansDT-Light", "size": 1}}, {"id_box": 226892, "box": [116.93084957888988, 178.1004571977685, 787.8455602774384, 162.89078809137152], "id_box_line": 40, "box_line": [718.959205887246, 297.2815143521493, 4.566214953156759, 10.489545313531607], "text": "-", "category": "Table", "words": [], "linking": [], "font": {"color": [0, 0, 0, 255], "name": "/JJSLPI+SenticoSansDT-Light", "size": 1}}, {"id_box": 226892, "box": [116.93084957888988, 178.1004571977685, 787.8455602774384, 162.89078809137152], "id_box_line": 41, "box_line": [771.3951292755486, 297.2815143521493, 37.90464647105739, 10.489545313531607], "text": "17,042", "category": "Table", "words": [], "linking": [], "font": {"color": [0, 0, 0, 255], "name": "/JJSLPI+SenticoSansDT-Light", "size": 1}}, {"id_box": 226892, "box": [116.93084957888988, 178.1004571977685, 787.8455602774384, 162.89078809137152], "id_box_line": 42, "box_line": [890.5075625117554, 297.2815143521493, 4.566265408570757, 10.489545313531607], "text": "-", "category": "Table", "words": [], "linking": [], "font": {"color": [0, 0, 0, 255], "name": "/JJSLPI+SenticoSansDT-Light", "size": 1}}, {"id_box": 226892, "box": [116.93084957888988, 178.1004571977685, 787.8455602774384, 162.89078809137152], "id_box_line": 43, "box_line": [119.1859400467934, 312.77735901526364, 57.51917851300988, 10.489545313531607], "text": "Borrowings", "category": "Table", "words": [], "linking": [], "font": {"color": [0, 0, 0, 255], "name": "/JJSLPI+SenticoSansDT-Light", "size": 1}}, {"id_box": 226892, "box": [116.93084957888988, 178.1004571977685, 787.8455602774384, 162.89078809137152], "id_box_line": 44, "box_line": [633.1850023472842, 312.77735901526364, 4.566214953156873, 10.489545313531607], "text": "-", "category": "Table", "words": [], "linking": [], "font": {"color": [0, 0, 0, 255], "name": "/JJSLPI+SenticoSansDT-Light", "size": 1}}, {"id_box": 226892, "box": [116.93084957888988, 178.1004571977685, 787.8455602774384, 162.89078809137152], "id_box_line": 45, "box_line": [692.6595064226624, 312.77735901526364, 30.86611623939575, 10.489545313531607], "text": "1,017", "category": "Table", "words": [], "linking": [], "font": {"color": [0, 0, 0, 255], "name": "/JJSLPI+SenticoSansDT-Light", "size": 1}}, {"id_box": 226892, "box": [116.93084957888988, 178.1004571977685, 787.8455602774384, 162.89078809137152], "id_box_line": 46, "box_line": [804.7334094272076, 312.77735901526364, 4.566214953156873, 10.489545313531607], "text": "-", "category": "Table", "words": [], "linking": [], "font": {"color": [0, 0, 0, 255], "name": "/JJSLPI+SenticoSansDT-Light", "size": 1}}, {"id_box": 226892, "box": [116.93084957888988, 178.1004571977685, 787.8455602774384, 162.89078809137152], "id_box_line": 47, "box_line": [864.2078630471718, 312.77735901526364, 30.866065783981867, 10.489545313531607], "text": "1,050", "category": "Table", "words": [], "linking": [], "font": {"color": [0, 0, 0, 255], "name": "/JJSLPI+SenticoSansDT-Light", "size": 1}}, {"id_box": 226892, "box": [116.93084957888988, 178.1004571977685, 787.8455602774384, 162.89078809137152], "id_box_line": 48, "box_line": [119.18612000443613, 326.60067489647463, 365.6982949286139, 12.42604000027768], "text": "Total financial liabilities at fair value through profit or loss", "category": "Table", "words": [], "linking": [], "font": {"color": [0, 112, 186, 255], "name": "/JJSLPI+SenticoSansDT-Bold", "size": 1}}, {"id_box": 226892, "box": [116.93084957888988, 178.1004571977685, 787.8455602774384, 162.89078809137152], "id_box_line": 49, "box_line": [594.5348098627519, 327.19475315256966, 43.21671017017229, 11.695045573774564], "text": "11,248", "category": "Table", "words": [], "linking": [], "font": {"color": [0, 112, 186, 255], "name": "/JJSLPI+SenticoSansDT-Bold", "size": 1}}, {"id_box": 226892, "box": [116.93084957888988, 178.1004571977685, 787.8455602774384, 162.89078809137152], "id_box_line": 50, "box_line": [680.3090134027136, 327.19475315256966, 43.21671017017218, 11.695045573774564], "text": "33,645", "category": "Table", "words": [], "linking": [], "font": {"color": [0, 112, 186, 255], "name": "/JJSLPI+SenticoSansDT-Bold", "size": 1}}, {"id_box": 226892, "box": [116.93084957888988, 178.1004571977685, 787.8455602774384, 162.89078809137152], "id_box_line": 51, "box_line": [766.0832169426752, 327.19475315256966, 43.21671017017229, 11.695045573774564], "text": "17,042", "category": "Table", "words": [], "linking": [], "font": {"color": [0, 112, 186, 255], "name": "/JJSLPI+SenticoSansDT-Bold", "size": 1}}, {"id_box": 226892, "box": [116.93084957888988, 178.1004571977685, 787.8455602774384, 162.89078809137152], "id_box_line": 52, "box_line": [851.8574204826369, 327.19475315256966, 43.21671017017229, 11.695045573774564], "text": "30,238", "category": "Table", "words": [], "linking": [], "font": {"color": [0, 112, 186, 255], "name": "/JJSLPI+SenticoSansDT-Bold", "size": 1}}]}