{"metadata": {"page_hash": "b17bdbda2be5ecf3b6a8e3597a2aa177e7a3a2c634fed09d7f7d2caf7250098e", "original_filename": "NYSE_AEG_2013.pdf", "page_no": 283, "num_pages": 358, "original_width": 609.44897, "original_height": 793.70099, "coco_width": 1025, "coco_height": 1025, "collection": "ann_reports_10_14_fancy", "doc_category": "financial_reports"}, "form": [{"id_box": 265101, "box": [927.3018703272236, 31.405408099592023, 25.883660940472055, 13.157034426780683], "id_box_line": 69, "box_line": [927.3018703272236, 31.405408099592023, 25.883660940472055, 13.157034426780683], "text": "283", "category": "Page-header", "words": [], "linking": [], "font": {"color": [135, 135, 135, 255], "name": "/JJSLPI+SenticoSansDT-Bold", "size": 1}}, {"id_box": 265102, "box": [120.13803706978123, 101.12576431333423, 786.1939241607053, 151.36134295359773], "id_box_line": 0, "box_line": [120.13803706978123, 101.12576431333423, 781.9462846905786, 11.888164269519166], "text": "The Management Board, which assists the Executive Board in pursuing Aegon\u2019s strategic goals, is formed by members of the Executive ", "category": "Text", "words": [], "linking": [], "font": {"color": [0, 0, 0, 255], "name": "/JJSLPI+SenticoSansDT-Light", "size": 1}}, {"id_box": 265102, "box": [120.13803706978123, 101.12576431333423, 786.1939241607053, 151.36134295359773], "id_box_line": 1, "box_line": [120.13803706978123, 116.6227841671207, 740.4186535912924, 11.88816426951928], "text": "Board, the CEO\u2019s of Aegon USA, Aegon the Netherlands, Aegon UK and Aegon Central & Eastern Europe and Aegon\u2019s Chief Risk ", "category": "Text", "words": [], "linking": [], "font": {"color": [0, 0, 0, 255], "name": "/JJSLPI+SenticoSansDT-Light", "size": 1}}, {"id_box": 265102, "box": [120.13803706978123, 101.12576431333423, 786.1939241607053, 151.36134295359773], "id_box_line": 2, "box_line": [120.13803706978123, 132.11980402090728, 780.168050903425, 11.888164269519166], "text": "Officer. The total remuneration for the members of the Management Board over 2013 was EUR 15.2 million (2012: EUR 13.8 million), ", "category": "Text", "words": [], "linking": [], "font": {"color": [0, 0, 0, 255], "name": "/JJSLPI+SenticoSansDT-Light", "size": 1}}, {"id_box": 265102, "box": [120.13803706978123, 101.12576431333423, 786.1939241607053, 151.36134295359773], "id_box_line": 3, "box_line": [120.13803706978123, 147.61682387469375, 703.1011904081156, 11.888164269519166], "text": "consisting of EUR 5.0 million (2012: EUR 4.1 million) fixed compensation, EUR 6.3 million variable compensation awards ", "category": "Text", "words": [], "linking": [], "font": {"color": [0, 0, 0, 255], "name": "/JJSLPI+SenticoSansDT-Light", "size": 1}}, {"id_box": 265102, "box": [120.13803706978123, 101.12576431333423, 786.1939241607053, 151.36134295359773], "id_box_line": 4, "box_line": [120.13803706978123, 163.11384372848022, 746.1126984101719, 11.888164269519166], "text": "(2012: EUR 6.2 million), EUR 1.3 million (2012: EUR 0.6 million) other benefits, EUR 1.6 million (2012: EUR 2.3 million) pension ", "category": "Text", "words": [], "linking": [], "font": {"color": [0, 0, 0, 255], "name": "/JJSLPI+SenticoSansDT-Light", "size": 1}}, {"id_box": 265102, "box": [120.13803706978123, 101.12576431333423, 786.1939241607053, 151.36134295359773], "id_box_line": 5, "box_line": [120.13803706978123, 178.6108635822667, 769.9507118701011, 11.88816426951928], "text": "premiums and EUR 1.0 million (2012: EUR 0.6 million) reflecting 16% crisis tax which was accrued for members of the Management ", "category": "Text", "words": [], "linking": [], "font": {"color": [0, 0, 0, 255], "name": "/JJSLPI+SenticoSansDT-Light", "size": 1}}, {"id_box": 265102, "box": [120.13803706978123, 101.12576431333423, 786.1939241607053, 151.36134295359773], "id_box_line": 6, "box_line": [120.13803706978123, 194.10788343605327, 742.635883115858, 11.888164269519166], "text": "Board employed in the Netherlands. Expenses as recognized under IFRS in the income statement for variable compensation and ", "category": "Text", "words": [], "linking": [], "font": {"color": [0, 0, 0, 255], "name": "/JJSLPI+SenticoSansDT-Light", "size": 1}}, {"id_box": 265102, "box": [120.13803706978123, 101.12576431333423, 786.1939241607053, 151.36134295359773], "id_box_line": 7, "box_line": [120.13803706978123, 209.60490328983974, 786.1939241607053, 11.888164269519166], "text": "pensions differ from the variable compensation awards and pension premiums paid due to the accounting treatment under respectively ", "category": "Text", "words": [], "linking": [], "font": {"color": [0, 0, 0, 255], "name": "/JJSLPI+SenticoSansDT-Light", "size": 1}}, {"id_box": 265102, "box": [120.13803706978123, 101.12576431333423, 786.1939241607053, 151.36134295359773], "id_box_line": 8, "box_line": [120.13803706978123, 225.1019231436262, 749.0663078813635, 11.888164269519166], "text": "IFRS 2 and IAS 19. IFRS expenses related to variable compensation amounted to EUR 6.3 million (2012: EUR 5.5 million) and for ", "category": "Text", "words": [], "linking": [], "font": {"color": [0, 0, 0, 255], "name": "/JJSLPI+SenticoSansDT-Light", "size": 1}}, {"id_box": 265102, "box": [120.13803706978123, 101.12576431333423, 786.1939241607053, 151.36134295359773], "id_box_line": 9, "box_line": [120.13803706978123, 240.59894299741268, 287.2306323694336, 11.88816426951928], "text": "pensions EUR 1.7 million (2012: EUR 1.4 million).", "category": "Text", "words": [], "linking": [], "font": {"color": [0, 0, 0, 255], "name": "/JJSLPI+SenticoSansDT-Light", "size": 1}}, {"id_box": 265103, "box": [120.13803706978123, 271.59298270498573, 777.1714366011644, 27.385184123305635], "id_box_line": 10, "box_line": [120.13803706978123, 271.59298270498573, 777.1714366011644, 11.888164269519166], "text": "Additional information on the remuneration and share-based compensation of members of the Executive Board and the remuneration ", "category": "Text", "words": [], "linking": [], "font": {"color": [0, 0, 0, 255], "name": "/JJSLPI+SenticoSansDT-Light", "size": 1}}, {"id_box": 265103, "box": [120.13803706978123, 271.59298270498573, 777.1714366011644, 27.385184123305635], "id_box_line": 11, "box_line": [120.13803706978123, 287.0900025587722, 697.1155132972002, 11.888164269519166], "text": "of the Supervisory Board is disclosed in the sections below (all amounts in EUR '000, except where indicated otherwise).", "category": "Text", "words": [], "linking": [], "font": {"color": [0, 0, 0, 255], "name": "/JJSLPI+SenticoSansDT-Light", "size": 1}}, {"id_box": 265104, "box": [120.13803706978123, 333.5810621201317, 776.5710339948558, 58.379223830878686], "id_box_line": 13, "box_line": [120.13803706978123, 333.5810621201317, 776.5710339948558, 11.888164269519166], "text": "The information below reflect the compensation and various related expenses for members of the Executive Board. Under the current ", "category": "Text", "words": [], "linking": [], "font": {"color": [0, 0, 0, 255], "name": "/JJSLPI+SenticoSansDT-Light", "size": 1}}, {"id_box": 265104, "box": [120.13803706978123, 333.5810621201317, 776.5710339948558, 58.379223830878686], "id_box_line": 14, "box_line": [120.13803706978123, 349.0780819739182, 773.4487688936449, 11.888164269519166], "text": "remuneration structure, introduced in 2011, rewards are paid out over a number years, or in the case of shares, vest over a number of ", "category": "Text", "words": [], "linking": [], "font": {"color": [0, 0, 0, 255], "name": "/JJSLPI+SenticoSansDT-Light", "size": 1}}, {"id_box": 265104, "box": [120.13803706978123, 333.5810621201317, 776.5710339948558, 58.379223830878686], "id_box_line": 15, "box_line": [120.13803706978123, 364.57514057025435, 775.5088970779619, 11.888125526969588], "text": "years. This remuneration-structure has made it more relevant to present rewards earned during a certain performance year instead of ", "category": "Text", "words": [], "linking": [], "font": {"color": [0, 0, 0, 255], "name": "/JJSLPI+SenticoSansDT-Light", "size": 1}}, {"id_box": 265104, "box": [120.13803706978123, 333.5810621201317, 776.5710339948558, 58.379223830878686], "id_box_line": 16, "box_line": [120.13803706978123, 380.07216042404093, 204.19975695422048, 11.888125526969475], "text": "what was received in a certain year.", "category": "Text", "words": [], "linking": [], "font": {"color": [0, 0, 0, 255], "name": "/JJSLPI+SenticoSansDT-Light", "size": 1}}, {"id_box": 265105, "box": [120.13786888506841, 690.0125574997708, 776.2135573877498, 58.379198002512226], "id_box_line": 55, "box_line": [120.13786888506841, 690.0125574997708, 735.2707381718931, 11.888138441152762], "text": "The amounts in the table represent the conditional variable compensation awards earned during the related performance year. ", "category": "Text", "words": [], "linking": [], "font": {"color": [0, 0, 0, 255], "name": "/JJSLPI+SenticoSansDT-Light", "size": 1}}, {"id_box": 265105, "box": [120.13786888506841, 690.0125574997708, 776.2135573877498, 58.379198002512226], "id_box_line": 56, "box_line": [120.13786888506841, 705.5095644393741, 747.2269557695698, 11.888151355335935], "text": "Expenses recognized under IFRS accounting treatment in the income statement for conditionally awarded cash and shares differ ", "category": "Text", "words": [], "linking": [], "font": {"color": [0, 0, 0, 255], "name": "/JJSLPI+SenticoSansDT-Light", "size": 1}}, {"id_box": 265105, "box": [120.13786888506841, 690.0125574997708, 776.2135573877498, 58.379198002512226], "id_box_line": 57, "box_line": [120.13786888506841, 721.0065842931606, 776.2135573877498, 11.888151355335992], "text": "from the awards. For the performance year 2013 and previous performance years, expenses under IFRS for Mr. Wynaendts amount to ", "category": "Text", "words": [], "linking": [], "font": {"color": [0, 0, 0, 255], "name": "/JJSLPI+SenticoSansDT-Light", "size": 1}}, {"id_box": 265105, "box": [120.13786888506841, 690.0125574997708, 776.2135573877498, 58.379198002512226], "id_box_line": 58, "box_line": [120.13786888506841, 736.503604146947, 179.0135748362984, 11.888151355335935], "text": "EUR 1,026 (2012: EUR 1.093).", "category": "Text", "words": [], "linking": [], "font": {"color": [0, 0, 0, 255], "name": "/JJSLPI+SenticoSansDT-Light", "size": 1}}, {"id_box": 265106, "box": [120.13786888506841, 767.4976438545201, 765.1273761279799, 73.87623077048195], "id_box_line": 59, "box_line": [120.13786888506841, 767.4976438545201, 759.3444793253158, 11.888151355335964], "text": "For Mr. Button, the expenses under IFRS with regard to conditionally awarded cash and shares recognized in the income statement ", "category": "Text", "words": [], "linking": [], "font": {"color": [0, 0, 0, 255], "name": "/JJSLPI+SenticoSansDT-Light", "size": 1}}, {"id_box": 265106, "box": [120.13786888506841, 767.4976438545201, 765.1273761279799, 73.87623077048195], "id_box_line": 60, "box_line": [120.13803706978123, 782.9946637083066, 765.1272079432671, 11.888151355335964], "text": "during the performance year 2013 for his role as CFO and member of Aegon\u2019s Executive Board amount to EUR 288. In performance ", "category": "Text", "words": [], "linking": [], "font": {"color": [0, 0, 0, 255], "name": "/JJSLPI+SenticoSansDT-Light", "size": 1}}, {"id_box": 265106, "box": [120.13786888506841, 767.4976438545201, 765.1273761279799, 73.87623077048195], "id_box_line": 61, "box_line": [120.13803706978123, 798.4916835620932, 761.5893079612555, 11.888151355335964], "text": "year 2013 and previous performance years Mr. Button has been awarded with variable compensation in his role as CFO of Americas ", "category": "Text", "words": [], "linking": [], "font": {"color": [0, 0, 0, 255], "name": "/JJSLPI+SenticoSansDT-Light", "size": 1}}, {"id_box": 265106, "box": [120.13786888506841, 767.4976438545201, 765.1273761279799, 73.87623077048195], "id_box_line": 62, "box_line": [120.13786888506841, 813.9887034158796, 753.7932737830372, 11.888151355335964], "text": "and Head of Corporate Financial Center. The related expenses under IFRS for those awards recognized in 2013 for the period that ", "category": "Text", "words": [], "linking": [], "font": {"color": [0, 0, 0, 255], "name": "/JJSLPI+SenticoSansDT-Light", "size": 1}}, {"id_box": 265106, "box": [120.13786888506841, 767.4976438545201, 765.1273761279799, 73.87623077048195], "id_box_line": 63, "box_line": [120.13786888506841, 829.4857232696661, 402.1066608743305, 11.888151355335964], "text": "Mr. Button has been part of the Executive Board amount to EUR 500.", "category": "Text", "words": [], "linking": [], "font": {"color": [0, 0, 0, 255], "name": "/JJSLPI+SenticoSansDT-Light", "size": 1}}, {"id_box": 265107, "box": [120.13786888506841, 860.479762977239, 756.7202932511312, 73.87623206190028], "id_box_line": 64, "box_line": [120.13786888506841, 860.479762977239, 756.7202932511312, 11.888151355335992], "text": "Expenses recognized in the income statement for Mr. Nooitgedagt amount to EUR 836 (2012: 736). Under IFRS, expenses related ", "category": "Text", "words": [], "linking": [], "font": {"color": [0, 0, 0, 255], "name": "/JJSLPI+SenticoSansDT-Light", "size": 1}}, {"id_box": 265107, "box": [120.13786888506841, 860.479762977239, 756.7202932511312, 73.87623206190028], "id_box_line": 65, "box_line": [120.13786888506841, 875.9767828310256, 756.0046000241824, 11.888151355335992], "text": "to conditional variable compensation awards are recognized in full at retirement date. Therefore, expenses under IFRS in 2013 for ", "category": "Text", "words": [], "linking": [], "font": {"color": [0, 0, 0, 255], "name": "/JJSLPI+SenticoSansDT-Light", "size": 1}}, {"id_box": 265107, "box": [120.13786888506841, 860.479762977239, 756.7202932511312, 73.87623206190028], "id_box_line": 66, "box_line": [120.13786888506841, 891.4738026848121, 735.1264525067619, 11.888152646754293], "text": "Mr. Nooitgedagt relate to the conditional variable compensation awards for the performance year 2013 as well as for previous ", "category": "Text", "words": [], "linking": [], "font": {"color": [0, 0, 0, 255], "name": "/JJSLPI+SenticoSansDT-Light", "size": 1}}, {"id_box": 265107, "box": [120.13786888506841, 860.479762977239, 756.7202932511312, 73.87623206190028], "id_box_line": 67, "box_line": [120.13786888506841, 906.9708264128535, 749.2376881037308, 11.88814877249932], "text": "performance years. The vesting conditions and applicable holding periods for the awards of Mr. Nooitgedagt remain nevertheless ", "category": "Text", "words": [], "linking": [], "font": {"color": [0, 0, 0, 255], "name": "/JJSLPI+SenticoSansDT-Light", "size": 1}}, {"id_box": 265107, "box": [120.13786888506841, 860.479762977239, 756.7202932511312, 73.87623206190028], "id_box_line": 68, "box_line": [120.13786888506841, 922.4678462666401, 66.5607853107045, 11.88814877249932], "text": "unchanged.", "category": "Text", "words": [], "linking": [], "font": {"color": [0, 0, 0, 255], "name": "/JJSLPI+SenticoSansDT-Light", "size": 1}}, {"id_box": 265110, "box": [120.13786888506841, 642.1510577301913, 772.6837807273675, 21.361970330917757], "id_box_line": 50, "box_line": [120.13786888506841, 642.1510577301913, 5.477167267999491, 5.707733210714537], "text": "1 ", "category": "Text", "words": [], "linking": [], "font": {"color": [0, 0, 0, 255], "name": "/JJSLPI+SenticoSansDT-Light", "size": 1}}, {"id_box": 265110, "box": [120.13786888506841, 642.1510577301913, 772.6837807273675, 21.361970330917757], "id_box_line": 51, "box_line": [129.672771536557, 642.745730038714, 763.148878075879, 9.79024229262967], "text": "Mr. Button was appointed as CFO and member of Aegon\u2019s Executive Board per May 15, 2013. Conditional variable compensation is disclosed for the period that ", "category": "Text", "words": [], "linking": [], "font": {"color": [0, 0, 0, 255], "name": "/JJSLPI+SenticoSansDT-Light", "size": 1}}, {"id_box": 265110, "box": [120.13786888506841, 642.1510577301913, 772.6837807273675, 21.361970330917757], "id_box_line": 52, "box_line": [129.672771536557, 653.7227857684795, 232.0055774316921, 9.790242292629614], "text": "Mr. Button has been part of the Executive Board.", "category": "Text", "words": [], "linking": [], "font": {"color": [0, 0, 0, 255], "name": "/JJSLPI+SenticoSansDT-Light", "size": 1}}, {"id_box": 265111, "box": [120.13786888506841, 664.1089143028536, 610.040216000365, 10.384914601152218], "id_box_line": 53, "box_line": [120.13786888506841, 664.1089143028536, 5.477167267999491, 5.70773321071448], "text": "2 ", "category": "Text", "words": [], "linking": [], "font": {"color": [0, 0, 0, 255], "name": "/JJSLPI+SenticoSansDT-Light", "size": 1}}, {"id_box": 265111, "box": [120.13786888506841, 664.1089143028536, 610.040216000365, 10.384914601152218], "id_box_line": 54, "box_line": [129.672771536557, 664.7035866113763, 600.5053133488765, 9.790242292629557], "text": "Mr. Nooitgedagt\u2019s conditional variable compensation is reflective of his time with Aegon till retirement as per August 1, 2013.", "category": "Text", "words": [], "linking": [], "font": {"color": [0, 0, 0, 255], "name": "/JJSLPI+SenticoSansDT-Light", "size": 1}}, {"id_box": 265112, "box": [120.13803706978123, 502.6778790461128, 776.3214815179684, 21.361970330917813], "id_box_line": 31, "box_line": [120.13803706978123, 502.6778790461128, 5.477165586152353, 5.707733210714537], "text": "1 ", "category": "Text", "words": [], "linking": [], "font": {"color": [0, 0, 0, 255], "name": "/JJSLPI+SenticoSansDT-Light", "size": 1}}, {"id_box": 265112, "box": [120.13803706978123, 502.6778790461128, 776.3214815179684, 21.361970330917813], "id_box_line": 32, "box_line": [129.672771536557, 503.27255135463554, 766.7867470511927, 9.790242292629614], "text": "Mr. Button was appointed as CFO and member of Aegon\u2019s Executive Board per May 15, 2013. Fixed compensation is disclosed for the period that Mr. Button has ", "category": "Text", "words": [], "linking": [], "font": {"color": [0, 0, 0, 255], "name": "/JJSLPI+SenticoSansDT-Light", "size": 1}}, {"id_box": 265112, "box": [120.13803706978123, 502.6778790461128, 776.3214815179684, 21.361970330917813], "id_box_line": 33, "box_line": [129.672771536557, 514.249607084401, 159.3324752850103, 9.79024229262967], "text": "been part of the Executive Board.", "category": "Text", "words": [], "linking": [], "font": {"color": [0, 0, 0, 255], "name": "/JJSLPI+SenticoSansDT-Light", "size": 1}}, {"id_box": 265113, "box": [120.13803706978123, 524.635735618775, 540.5680221266105, 10.384914601152218], "id_box_line": 34, "box_line": [120.13803706978123, 524.635735618775, 5.477165586152353, 5.707733210714537], "text": "2 ", "category": "Text", "words": [], "linking": [], "font": {"color": [0, 0, 0, 255], "name": "/JJSLPI+SenticoSansDT-Light", "size": 1}}, {"id_box": 265113, "box": [120.13803706978123, 524.635735618775, 540.5680221266105, 10.384914601152218], "id_box_line": 35, "box_line": [129.672771536557, 525.2304079272977, 531.0332876598347, 9.790242292629557], "text": "Mr. Nooitgedagt\u2019s fixed compensation is reflective of his time with Aegon till retirement as per August 1, 2013.", "category": "Text", "words": [], "linking": [], "font": {"color": [0, 0, 0, 255], "name": "/JJSLPI+SenticoSansDT-Light", "size": 1}}, {"id_box": 265114, "box": [120.13803706978123, 316.9411241379453, 373.67328605051205, 13.157034426780797], "id_box_line": 12, "box_line": [120.13803706978123, 316.9411241379453, 373.67328605051205, 13.157034426780797], "text": "Remuneration of active members of the Executive Board ", "category": "Section-header", "words": [], "linking": [], "font": {"color": [0, 112, 186, 255], "name": "/JJSLPI+SenticoSansDT-Bold", "size": 1}}, {"id_box": 265115, "box": [120.13803706978123, 410.31845600948554, 125.02851887665017, 12.761782935409883], "id_box_line": 17, "box_line": [120.13803706978123, 410.31845600948554, 125.02851887665017, 12.761782935409883], "text": "Fixed compensation", "category": "Section-header", "words": [], "linking": [], "font": {"color": [0, 112, 186, 255], "name": "/JJSLPI+SenticoSansDT-Regular", "size": 1}}, {"id_box": 265116, "box": [120.13803706978123, 549.791634693564, 264.8001063157101, 12.761782935409883], "id_box_line": 36, "box_line": [120.13803706978123, 549.791634693564, 264.8001063157101, 12.761782935409883], "text": "Conditional variable compensation awards", "category": "Section-header", "words": [], "linking": [], "font": {"color": [0, 112, 186, 255], "name": "/JJSLPI+SenticoSansDT-Regular", "size": 1}}, {"id_box": 265117, "box": [119.46932497529636, 572.6715489194415, 786.2135724477222, 66.77795597353219], "id_box_line": 37, "box_line": [777.67768604154, 577.1091484968414, 33.73785339238498, 12.426040000277737], "text": "2013", "category": "Table", "words": [], "linking": [], "font": {"color": [0, 112, 186, 255], "name": "/JJSLPI+SenticoSansDT-Bold", "size": 1}}, {"id_box": 265117, "box": [119.46932497529636, 572.6715489194415, 786.2135724477222, 66.77795597353219], "id_box_line": 38, "box_line": [867.1971949513672, 578.2197811672127, 30.03109595869853, 11.188848334433828], "text": "2012", "category": "Table", "words": [], "linking": [], "font": {"color": [0, 0, 0, 255], "name": "/JJSLPI+SenticoSansDT-Light", "size": 1}}, {"id_box": 265117, "box": [119.46932497529636, 572.6715489194415, 786.2135724477222, 66.77795597353219], "id_box_line": 39, "box_line": [120.13803706978123, 594.2772636581947, 124.92759123048481, 10.489545313531721], "text": "Alexander R. Wynaendts", "category": "Table", "words": [], "linking": [], "font": {"color": [0, 0, 0, 255], "name": "/JJSLPI+SenticoSansDT-Light", "size": 1}}, {"id_box": 265117, "box": [119.46932497529636, 572.6715489194415, 786.2135724477222, 66.77795597353219], "id_box_line": 40, "box_line": [780.5494736499431, 594.2772636581947, 30.866116239395637, 10.489545313531721], "text": "1,032", "category": "Table", "words": [], "linking": [], "font": {"color": [0, 0, 0, 255], "name": "/JJSLPI+SenticoSansDT-Light", "size": 1}}, {"id_box": 265117, "box": [119.46932497529636, 572.6715489194415, 786.2135724477222, 66.77795597353219], "id_box_line": 41, "box_line": [866.362225126084, 594.2772636581947, 30.866065783981753, 10.489545313531721], "text": "1,018", "category": "Table", "words": [], "linking": [], "font": {"color": [0, 0, 0, 255], "name": "/JJSLPI+SenticoSansDT-Light", "size": 1}}, {"id_box": 265117, "box": [119.46932497529636, 572.6715489194415, 786.2135724477222, 66.77795597353219], "id_box_line": 42, "box_line": [120.13786888506841, 609.7731083213089, 85.49670212749724, 10.489545313531721], "text": "Darryl D. Button ", "category": "Table", "words": [], "linking": [], "font": {"color": [0, 0, 0, 255], "name": "/JJSLPI+SenticoSansDT-Light", "size": 1}}, {"id_box": 265117, "box": [119.46932497529636, 572.6715489194415, 786.2135724477222, 66.77795597353219], "id_box_line": 43, "box_line": [205.63238461129893, 610.6041618393346, 5.772301165756346, 5.707733210714537], "text": "1)", "category": "Table", "words": [], "linking": [], "font": {"color": [0, 0, 0, 255], "name": "/JJSLPI+SenticoSansDT-Light", "size": 1}}, {"id_box": 265117, "box": [119.46932497529636, 572.6715489194415, 786.2135724477222, 66.77795597353219], "id_box_line": 44, "box_line": [790.2997973726988, 609.7731083213089, 21.11559069498469, 10.489545313531721], "text": "468", "category": "Table", "words": [], "linking": [], "font": {"color": [0, 0, 0, 255], "name": "/JJSLPI+SenticoSansDT-Light", "size": 1}}, {"id_box": 265117, "box": [119.46932497529636, 572.6715489194415, 786.2135724477222, 66.77795597353219], "id_box_line": 45, "box_line": [892.6619245906676, 609.7731083213089, 4.566248590099235, 10.489545313531721], "text": "-", "category": "Table", "words": [], "linking": [], "font": {"color": [0, 0, 0, 255], "name": "/JJSLPI+SenticoSansDT-Light", "size": 1}}, {"id_box": 265117, "box": [119.46932497529636, 572.6715489194415, 786.2135724477222, 66.77795597353219], "id_box_line": 46, "box_line": [120.13786888506841, 625.2688238425909, 94.74265671496663, 10.489545313531778], "text": "Jan J. Nooitgedagt ", "category": "Table", "words": [], "linking": [], "font": {"color": [0, 0, 0, 255], "name": "/JJSLPI+SenticoSansDT-Light", "size": 1}}, {"id_box": 265117, "box": [119.46932497529636, 572.6715489194415, 786.2135724477222, 66.77795597353219], "id_box_line": 47, "box_line": [214.87850738348118, 626.0998902747999, 5.772284347285051, 5.707720296531363], "text": "2)", "category": "Table", "words": [], "linking": [], "font": {"color": [0, 0, 0, 255], "name": "/JJSLPI+SenticoSansDT-Light", "size": 1}}, {"id_box": 265117, "box": [119.46932497529636, 572.6715489194415, 786.2135724477222, 66.77795597353219], "id_box_line": 48, "box_line": [790.2997973726988, 625.2688238425909, 21.11559069498469, 10.489545313531778], "text": "434", "category": "Table", "words": [], "linking": [], "font": {"color": [0, 0, 0, 255], "name": "/JJSLPI+SenticoSansDT-Light", "size": 1}}, {"id_box": 265117, "box": [119.46932497529636, 572.6715489194415, 786.2135724477222, 66.77795597353219], "id_box_line": 49, "box_line": [876.1127002150811, 625.2688238425909, 21.11559069498469, 10.489545313531778], "text": "699", "category": "Table", "words": [], "linking": [], "font": {"color": [0, 0, 0, 255], "name": "/JJSLPI+SenticoSansDT-Light", "size": 1}}, {"id_box": 265118, "box": [115.95552129955234, 431.6958640864291, 791.4842779613384, 68.12700558915913], "id_box_line": 18, "box_line": [777.67768604154, 437.63596981276294, 33.73785339238498, 12.42604000027768], "text": "2013", "category": "Table", "words": [], "linking": [], "font": {"color": [0, 112, 186, 255], "name": "/JJSLPI+SenticoSansDT-Bold", "size": 1}}, {"id_box": 265118, "box": [115.95552129955234, 431.6958640864291, 791.4842779613384, 68.12700558915913], "id_box_line": 19, "box_line": [867.1971949513672, 438.7466024831342, 30.03109595869853, 11.188848334433828], "text": "2012", "category": "Table", "words": [], "linking": [], "font": {"color": [0, 0, 0, 255], "name": "/JJSLPI+SenticoSansDT-Light", "size": 1}}, {"id_box": 265118, "box": [115.95552129955234, 431.6958640864291, 791.4842779613384, 68.12700558915913], "id_box_line": 20, "box_line": [120.13803706978123, 454.8040849741161, 124.92759123048481, 10.489545313531721], "text": "Alexander R. Wynaendts", "category": "Table", "words": [], "linking": [], "font": {"color": [0, 0, 0, 255], "name": "/JJSLPI+SenticoSansDT-Light", "size": 1}}, {"id_box": 265118, "box": [115.95552129955234, 431.6958640864291, 791.4842779613384, 68.12700558915913], "id_box_line": 21, "box_line": [780.5494736499431, 454.8040849741161, 30.866116239395637, 10.489545313531721], "text": "1,049", "category": "Table", "words": [], "linking": [], "font": {"color": [0, 0, 0, 255], "name": "/JJSLPI+SenticoSansDT-Light", "size": 1}}, {"id_box": 265118, "box": [115.95552129955234, 431.6958640864291, 791.4842779613384, 68.12700558915913], "id_box_line": 22, "box_line": [866.3623260369117, 454.8040849741161, 30.866065783981867, 10.489545313531721], "text": "1,049", "category": "Table", "words": [], "linking": [], "font": {"color": [0, 0, 0, 255], "name": "/JJSLPI+SenticoSansDT-Light", "size": 1}}, {"id_box": 265118, "box": [115.95552129955234, 431.6958640864291, 791.4842779613384, 68.12700558915913], "id_box_line": 23, "box_line": [120.13803706978123, 470.2999296372303, 85.49670212749723, 10.489545313531721], "text": "Darryl D. Button ", "category": "Table", "words": [], "linking": [], "font": {"color": [0, 0, 0, 255], "name": "/JJSLPI+SenticoSansDT-Light", "size": 1}}, {"id_box": 265118, "box": [115.95552129955234, 431.6958640864291, 791.4842779613384, 68.12700558915913], "id_box_line": 24, "box_line": [205.63255279601177, 471.1309831552561, 5.772301165756346, 5.707733210714537], "text": "1)", "category": "Table", "words": [], "linking": [], "font": {"color": [0, 0, 0, 255], "name": "/JJSLPI+SenticoSansDT-Light", "size": 1}}, {"id_box": 265118, "box": [115.95552129955234, 431.6958640864291, 791.4842779613384, 68.12700558915913], "id_box_line": 25, "box_line": [790.2999487389403, 470.2999296372303, 21.11559069498469, 10.489545313531721], "text": "475", "category": "Table", "words": [], "linking": [], "font": {"color": [0, 0, 0, 255], "name": "/JJSLPI+SenticoSansDT-Light", "size": 1}}, {"id_box": 265118, "box": [115.95552129955234, 431.6958640864291, 791.4842779613384, 68.12700558915913], "id_box_line": 26, "box_line": [892.6620255014951, 470.2999296372303, 4.566265408570644, 10.489545313531721], "text": "-", "category": "Table", "words": [], "linking": [], "font": {"color": [0, 0, 0, 255], "name": "/JJSLPI+SenticoSansDT-Light", "size": 1}}, {"id_box": 265118, "box": [115.95552129955234, 431.6958640864291, 791.4842779613384, 68.12700558915913], "id_box_line": 27, "box_line": [120.13803706978123, 485.79564515851246, 94.74263989649535, 10.489545313531721], "text": "Jan J. Nooitgedagt ", "category": "Table", "words": [], "linking": [], "font": {"color": [0, 0, 0, 255], "name": "/JJSLPI+SenticoSansDT-Light", "size": 1}}, {"id_box": 265118, "box": [115.95552129955234, 431.6958640864291, 791.4842779613384, 68.12700558915913], "id_box_line": 28, "box_line": [214.87867556819398, 486.62671159072136, 5.772301165756318, 5.70772029653142], "text": "2)", "category": "Table", "words": [], "linking": [], "font": {"color": [0, 0, 0, 255], "name": "/JJSLPI+SenticoSansDT-Light", "size": 1}}, {"id_box": 265118, "box": [115.95552129955234, 431.6958640864291, 791.4842779613384, 68.12700558915913], "id_box_line": 29, "box_line": [790.2999487389403, 485.79564515851246, 21.11559069498469, 10.489545313531721], "text": "434", "category": "Table", "words": [], "linking": [], "font": {"color": [0, 0, 0, 255], "name": "/JJSLPI+SenticoSansDT-Light", "size": 1}}, {"id_box": 265118, "box": [115.95552129955234, 431.6958640864291, 791.4842779613384, 68.12700558915913], "id_box_line": 30, "box_line": [876.1127002150811, 485.79564515851246, 21.11559069498469, 10.489545313531721], "text": "744", "category": "Table", "words": [], "linking": [], "font": {"color": [0, 0, 0, 255], "name": "/JJSLPI+SenticoSansDT-Light", "size": 1}}]}